README.md
setup.py
src/odhpy/__init__.py
src/odhpy/demo.py
src/odhpy/version.py
src/odhpy.egg-info/PKG-INFO
src/odhpy.egg-info/SOURCES.txt
src/odhpy.egg-info/dependency_links.txt
src/odhpy.egg-info/requires.txt
src/odhpy.egg-info/top_level.txt
src/odhpy/clim/__init__.py
src/odhpy/clim/clim.py
src/odhpy/io/__init__.py
src/odhpy/io/csv_io.py
src/odhpy/io/general_io.py
src/odhpy/io/idx_io.py
src/odhpy/io/idx_io_native.py
src/odhpy/io/iqqm_out_reader.py
src/odhpy/io/lqn_io.py
src/odhpy/io/res_csv_io.py
src/odhpy/maps/__init__.py
src/odhpy/maps/station_maps.py
src/odhpy/plots/__init__.py
src/odhpy/plots/altair_plots.py
src/odhpy/plots/node_diagrams.py
src/odhpy/plots/plot_functions.py
src/odhpy/plots/plotly_helpers.py
src/odhpy/plots/tests/__init__.py
src/odhpy/plots/tests/test_plot_functions.py
src/odhpy/stats/__init__.py
src/odhpy/stats/aggregate_stats.py
src/odhpy/stats/reliability_stats_class.py
src/odhpy/stats/storage_level_assessment.py
src/odhpy/stats/swflo2s/__init__.py
src/odhpy/stats/swflo2s/swflo2s.py
src/odhpy/stoch/__init__.py
src/odhpy/stoch/analyse.py
src/odhpy/stoch/generate.py
src/odhpy/trans/__init__.py
src/odhpy/trans/transformers.py
src/odhpy/utils/__init__.py
src/odhpy/utils/dataframe_extensions.py
src/odhpy/utils/dataframe_functions.py
src/odhpy/utils/datetime_functions.py
src/odhpy/utils/interpolation.py