Metadata-Version: 2.1
Name: odhpy
Version: 0.2.6
Summary: A collection of splashings to master that which has no form and count that which is uncountable.
Home-page: https://bitbucket.org/odhydrology/odhpy.git
Author: Chas Egan
Author-email: chas@odhydrology.com
Classifier: Programming Language :: Python :: 3
Classifier: Operating System :: OS Independent
Requires-Python: >=3.9
Requires-Dist: altair>=5.0.1
Requires-Dist: folium>=0.14
Requires-Dist: matplotlib>=3.8.3
Requires-Dist: numpy>=1.26.4
Requires-Dist: pandas>=2.2.0
Requires-Dist: plotly>=5.18.0
